Workbook
Name aporte: 'Controle de Investimentos'!$D$15
Name qtd_anos: 'Controle de Investimentos'!$D$16
Name rendimento_carteira: 'Controle de Investimentos'!$D$11
Name salario: 'Controle de Investimentos'!$D$10
Name taxa_mensal: 'Controle de Investimentos'!$D$17

Sheet Controle de Investimentos
B9: CONFIGURAÇÕES
B10: Salário | D10: 6000
B11: Rendimento carteira | D11: 0.006
B12: Sugestão de investimento (30% do salário) | D12: =D10*30% -> 1800
B14: INVESTIMENTO MENSAL
B15: Quanto investir por mês? | D15: 600
B16: Por quantos anos? | D16: 5
B17: Taxa de rendimento mensal? | D17: 0.01079
B18: Patrimônio acumulado? | D18: =FV(taxa_mensal,qtd_anos*12,aporte*-1) -> 50266.148
B19: Dividentos mensais? | D19: =D18*1% -> 502.66148
B21: CENÁRIOS | D21: Dividendo
A22: 2 | B22: Quanto em 2 anos? | C22: =FV($D$17,$A22*12,$D$15*-1) -> 16336.576 | D22: =C22*$D$11 -> 98.019458
A23: 5 | B23: Quanto em 5 anos? | C23: =FV($D$17,$A23*12,$D$15*-1) -> 50266.148 | D23: =C23*$D$11 -> 301.59689
A24: 10 | B24: Quanto em 10 anos? | C24: =FV($D$17,$A24*12,$D$15*-1) -> 145970.53 | D24: =C24*$D$11 -> 875.82317
A25: 20 | B25: Quanto em 20 anos? | C25: =FV($D$17,$A25*12,$D$15*-1) -> 675119.04 | D25: =C25*$D$11 -> 4050.7142
A26: 30 | B26: Quanto em 30 anos? | C26: =FV($D$17,$A26*12,$D$15*-1) -> 2593301.8 | D26: =C26*$D$11 -> 15559.811
B30: PERFIL | D30: CONSERVADOR
B31: Valor a ser investido por mês | D31: =aporte -> 600
B33: Tipo de FII | C33: Percentual sugerido | D33: Valores
B34: PAPEL | C34: =VLOOKUP($D$30&"-"&B34,'Tabela de apoio'!$B:$E,4,FALSE) -> 0.3 | D34: =C34*$D$31 -> 180
B35: TIJOLO | C35: =VLOOKUP($D$30&"-"&B35,'Tabela de apoio'!$B:$E,4,FALSE) -> 0.5 | D35: =C35*$D$31 -> 300
B36: HÍBRIDOS | C36: =VLOOKUP($D$30&"-"&B36,'Tabela de apoio'!$B:$E,4,FALSE) -> 0.1 | D36: =C36*$D$31 -> 60
B37: FOFs | C37: =VLOOKUP($D$30&"-"&B37,'Tabela de apoio'!$B:$E,4,FALSE) -> 0.1 | D37: =C37*$D$31 -> 60
B38: DESENVOLVIMENTO | C38: =VLOOKUP($D$30&"-"&B38,'Tabela de apoio'!$B:$E,4,FALSE) -> 0 | D38: =C38*$D$31 -> 0
B39: HOTELARIAS | C39: =VLOOKUP($D$30&"-"&B39,'Tabela de apoio'!$B:$E,4,FALSE) -> 0 | D39: =C39*$D$31 -> 0
D40: =SUM(D34:D39) -> 600

Sheet Tabela de apoio
A5: TABELA DE APOIO
B7: Chave composta | C7: Perfil | D7: Tipo de FII | E7: Percentual sugerido
B8: =$C$8&"-"&D8 -> CONSERVADOR-PAPEL | C8: CONSERVADOR | D8: PAPEL | E8: 0.3
B9: =$C$8&"-"&D9 -> CONSERVADOR-TIJOLO | C9: CONSERVADOR | D9: TIJOLO | E9: 0.5
B10: =$C$8&"-"&D10 -> CONSERVADOR-HÍBRIDOS | C10: CONSERVADOR | D10: HÍBRIDOS | E10: 0.1
B11: =$C$8&"-"&D11 -> CONSERVADOR-FOFs | C11: CONSERVADOR | D11: FOFs | E11: 0.1
B12: =$C$8&"-"&D12 -> CONSERVADOR-DESENVOLVIMENTO | C12: CONSERVADOR | D12: DESENVOLVIMENTO | E12: 0
B13: =$C$8&"-"&D13 -> CONSERVADOR-HOTELARIAS | C13: CONSERVADOR | D13: HOTELARIAS | E13: 0
B15: =$C$15&"-"&D15 -> MODERADO-PAPEL | C15: MODERADO | D15: PAPEL | E15: 0.32
B16: =$C$15&"-"&D16 -> MODERADO-TIJOLO | C16: MODERADO | D16: TIJOLO | E16: 0.35
B17: =$C$15&"-"&D17 -> MODERADO-HÍBRIDOS | C17: MODERADO | D17: HÍBRIDOS | E17: 0.08
B18: =$C$15&"-"&D18 -> MODERADO-FOFs | C18: MODERADO | D18: FOFs | E18: 0.05
B19: =$C$15&"-"&D19 -> MODERADO-DESENVOLVIMENTO | C19: MODERADO | D19: DESENVOLVIMENTO | E19: 0.1
B20: =$C$15&"-"&D20 -> MODERADO-HOTELARIAS | C20: MODERADO | D20: HOTELARIAS | E20: 0.1
B22: =$C$22&"-"&D22 -> AGRESSIVO-PAPEL | C22: AGRESSIVO | D22: PAPEL | E22: 0.5
B23: =$C$22&"-"&D23 -> AGRESSIVO-TIJOLO | C23: AGRESSIVO | D23: TIJOLO | E23: 0.1
B24: =$C$22&"-"&D24 -> AGRESSIVO-HÍBRIDOS | C24: AGRESSIVO | D24: HÍBRIDOS | E24: 0.05
B25: =$C$22&"-"&D25 -> AGRESSIVO-FOFs | C25: AGRESSIVO | D25: FOFs | E25: 0.05
B26: =$C$22&"-"&D26 -> AGRESSIVO-DESENVOLVIMENTO | C26: AGRESSIVO | D26: DESENVOLVIMENTO | E26: 0.2
B27: =$C$22&"-"&D27 -> AGRESSIVO-HOTELARIAS | C27: AGRESSIVO | D27: HOTELARIAS | E27: 0.1

Sheet Descrição
A2: TABELA DESCRITIVA
A3: Tipo de FII | B3: Descrição | C3: Exemplos de Ativos
A4: FII de Tijolo | B4: Investem diretamente em imóveis físicos com o objetivo de gerar renda por meio de aluguel. | C4: Shoppings, galpões logísticos, escritórios, hospitais
A5: FII de Papel | B5: Investem em títulos e valores mobiliários ligados ao setor imobiliário. | C5: CRIs (Certificados de Recebíveis Imobiliários), LCIs, cotas de outros FIIs
A6: FII Híbrido | B6: Combinam ativos de tijolo e de papel, buscando diversificação e flexibilidade. | C6: Combinação de imóveis físicos e CRIs
A7: FII de Desenvolvimento | B7: Focados na construção ou incorporação de imóveis para posterior venda ou locação. | C7: Loteamentos, prédios residenciais e comerciais em desenvolvimento
A8: FII de Fundos (FOF) | B8: Investem em cotas de outros FIIs, funcionando como um “fundo de fundos”. | C8: Carteiras diversificadas de FIIs
